Metadata-Version: 1.0
Name: three-in-a-row
Version: 0.1
Summary: Game of three in a row
Home-page: UNKNOWN
Author: UNKNOWN
Author-email: UNKNOWN
License: UNKNOWN
Platform: UNKNOWN
